pycountsvt/__init__.py
pycountsvt/plotting.py
pycountsvt/pycountsvt.py
pycountsvt-0.1.0.dist-info/LICENSE
pycountsvt-0.1.0.dist-info/WHEEL
pycountsvt-0.1.0.dist-info/METADATA
pycountsvt-0.1.0.dist-info/RECORD
